hyperx_mcp/__init__.py
hyperx_mcp/py.typed
hyperx_mcp/server.py
hyperx_mcp-0.1.2.dist-info/METADATA
hyperx_mcp-0.1.2.dist-info/WHEEL
hyperx_mcp-0.1.2.dist-info/entry_points.txt
hyperx_mcp-0.1.2.dist-info/RECORD
