Metadata-Version: 2.4
Name: hyperx-mcp
Version: 0.1.2
Summary: MCP server for HyperX - connect Claude to your knowledge graph
Project-URL: Homepage, https://hyperxdb.dev
Project-URL: Documentation, https://hyperxdb.dev/docs/mcp
Project-URL: Repository, https://github.com/hyperxdb/hyperx
Author-email: HyperX <hello@hyperxdb.dev>
License-Expression: MIT
Keywords: ai,anthropic,claude,hypergraph,knowledge-graph,mcp
Classifier: Development Status :: 3 - Alpha
Classifier: Intended Audience :: Developers
Classifier: License :: OSI Approved :: MIT License
Classifier: Programming Language :: Python :: 3
Classifier: Programming Language :: Python :: 3.10
Classifier: Programming Language :: Python :: 3.11
Classifier: Programming Language :: Python :: 3.12
Requires-Python: >=3.10
Requires-Dist: hyperxdb>=0.6.0
Requires-Dist: mcp>=1.0.0
Requires-Dist: pydantic>=2.0.0
Provides-Extra: dev
Requires-Dist: pytest-asyncio>=0.23.0; extra == 'dev'
Requires-Dist: pytest>=8.0.0; extra == 'dev'
Requires-Dist: ruff>=0.4.0; extra == 'dev'
